{
"travel":{
          "event":"",
          "rest":"",
          "bussines":"",
          "adventure":""
         },
"work":{
           "sale":"",
           "make":"",
           "trade":"",
           "solve":"",
           "communication":"",
           "stetic":""
        },
"game":{
          "azar":"",
          "sport":"",
          "table":"",
          "collaboration":""
          },
"person":{
           "family":"",
           "tribe":"",
           "enterprise":"",
           "inc":"",
           "horde":"",
           "clan":"",
           "personal":""
           "couple":""
          },
"software":{
            "app":"",
            "game":"",
            "api":""
          
           },
"machine":{
          "transport":"",
          "maker":"",
          "soft":"",
          "destroller":""
               
          },
"process":{
           "knowledge":"",
           "empiric":"",
           "work":"",
           "game":"",
           "social":"",
           "bilogic":"",
           "quemical":""
          },
"art":{
          "music":"",
          "paint":"",
          "architect":"",
          "sculpture":"",
          "dance":"",
          "literature":"",
          "cine":"",
          "visual":""
       },
"cook":{
         "dinner":"",
         "launch":"",
          "fast":"",
          "mexican":"",
          "italian":"",
          "greek":"",
          "frech":"",
          "spanish":""
         },
"music":{
          "classic":"",
          "jazz":"",
          "pop":"",
          "rock":"",
          "indie":""
          },
"culture":{
          "indian":"",
          "roman":"",
          "barroco":"",
          "greek":"",
          "classical":""
          "helenas":"",
          "akad":""
},
"novel":{
         "writter":"",
         "character":"", 
         "scenario":"",
         "period":"",
         "style":"",
         "reader":"" 
 },
"story":{
          "short":"",
          "long":"",
          "contry":"",
          "classical":"",
          "comic":"" 
       },
"religion":{
            "budism":"",
            "jewish":"",
            "christianism":"",
            "hinduism":"",
            "atheism":"",
            "celtic":"",
            "zoroatrism":""
           },
"philosofy":{
            "occidental":"",
            "socrates":"",
            "pragmatic":"",
            "communism":"",
            "scienciology":"",
            "romanticism":"",
            "socialism":"",
            "capitalism":""
            },
"object":{ 
             "AsCluster":"", 
             "AsPlanetary":"",
             "AsStar":"",
             "AsPlanet":"",
             "AsSatelit":"",
             "AsAsteroid":"",
             "AsSky":"",
             "AsMointain":"",
             "AsBuild":"",
             "AsRoom":"",
             "AsBigAnimal":"",
             "AsBigHandle":"",
             "AsHuman":"",
             "AsAnimal":"",
             "AsPet":"",
             "AsHandle":"",
             "AsFinger":"",
             "AsMiniHandle":"",
             "AsMicroHandle":"",
             "AsNanoHandle":"",
             "AsIndirectHandle":"",
             "AsEffectHandle":""
          },
  "place":{
             "imaginary":"",
             "abstract":"",
             "open":"",
             "close":"",
             "cave":"",
             "room":"",
             "sea":""
  }        
}
